ebofcis2/__init__.py
ebofcis2/modulo.py
ebofcis2-0.1.8.dist-info/METADATA
ebofcis2-0.1.8.dist-info/WHEEL
ebofcis2-0.1.8.dist-info/top_level.txt
ebofcis2-0.1.8.dist-info/RECORD
