Metadata-Version: 2.1
Name: ebofcis2
Version: 0.1.8
Summary: Libreria que contiene dos clases        Una para realizar integrales por método de montecarlo        y otra para realizar un ajuste de curva suavizado        con el método de kernel gaussiano
Author: Emmanuel Botero  
Author-email: emmanuel.botero@udea.edu.co
License: MIT
Requires-Python: >=3.10.12
Requires-Dist: sympy ==1.12
Requires-Dist: tqdm ==4.66.1
Requires-Dist: numpy ==1.26.1
Requires-Dist: pandas ==2.1.2
Requires-Dist: matplotlib ==3.8.1
